django_translate_gettext/__init__.py
django_translate_gettext/apps.py
django_translate_gettext/constants.py
django_translate_gettext/exceptions.py
django_translate_gettext/management/__init__.py
django_translate_gettext/management/commands/__init__.py
django_translate_gettext/management/commands/translate.py
django_translate_gettext/services/__init__.py
django_translate_gettext/services/files.py
django_translate_gettext/services/models.py
django_translate_gettext/services/transformers.py
django_translate_gettext/services/translators.py
django_translate_gettext-0.3.6.dist-info/LICENSE
django_translate_gettext-0.3.6.dist-info/METADATA
django_translate_gettext-0.3.6.dist-info/WHEEL
django_translate_gettext-0.3.6.dist-info/RECORD
