Metadata-Version: 2.1
Name: django-translate-gettext
Version: 0.3.6
Summary: Django app to wrap app files class fields to gettext calling for the given apps
Home-page: https://github.com/alpden550/django-translate-gettext
License: MIT
Keywords: django,django-orm,django app,ast,orm
Author: Denis Novikov
Author-email: alpden550@gmail.com
Requires-Python: >=3.11,<4.0
Classifier: Development Status :: 5 - Production/Stable
Classifier: Environment :: Web Environment
Classifier: Framework :: Django
Classifier: Framework :: Django :: 4.0
Classifier: Framework :: Django :: 4.2
Classifier: Framework :: Django :: 5.0
Classifier: Intended Audience :: Developers
Classifier: License :: OSI Approved :: MIT License
Classifier: Operating System :: OS Independent
Classifier: Programming Language :: Python
Classifier: Programming Language :: Python :: 3
Classifier: Programming Language :: Python :: 3.11
Classifier: Programming Language :: Python :: 3.12
Classifier: Programming Language :: Python :: 3.10
Classifier: Programming Language :: Python :: Implementation
Classifier: Topic :: Software Development
Classifier: Topic :: Utilities
Requires-Dist: deep-translator (>=1.11.4,<2.0.0)
Requires-Dist: django (>=4.0.1,<5.0.0)
Requires-Dist: loguru (>=0.7.2,<0.8.0)
Requires-Dist: ruff (>=0.4.3,<0.5.0)
Project-URL: Repository, https://github.com/alpden550/django-translate-gettext
